{
  "img": "modules/pf2e-soulbound-warrior/assets/PinkAlly.webp",
  "name": "Blessed Armament",
  "system": {
    "description": {
      "gm": "",
      "value": "<p>Select one weapon or handwraps of mighty blows. You gain that armament's critical specialization effect, and you grant the armament a property rune of your choice from the following list: @UUID[Compendium.pf2e.equipment-srd.Item.hnbbqvzYDyhDiJnf]{Bane}, @UUID[Compendium.pf2e.equipment-srd.Item.P6v2AtJw7AUwaDzf]{Fearsome}, @UUID[Compendium.pf2e.equipment-srd.Item.JQdwHECogcTzdd8R]{Ghost Touch}, @UUID[Compendium.pf2e.equipment-srd.Item.qlunQzfnzPQpMG6U]{Returning}, @UUID[Compendium.pf2e.equipment-srd.Item.roeYtwlIe65BPMJ1]{Shifting}, or @UUID[Compendium.pf2e.equipment-srd.Item.LwQb7ryTC8FlOXgX]{Vitalizing}. During your daily preparations, you can change the spirit to inhabit a different armament, grant a different rune, or both.</p><p>This rune doesn't count toward the weapon's number of property runes. It can be used even if the weapon already has its maximum number of property runes.</p>"
    },
    "rules": [
      {
        "suboptions": [
          {
            "label": "PF2E.WeaponPropertyRune.astral.Name",
            "predicate": [
              "feat:radiant-armament"
            ],
            "value": "astral"
          },
          {
            "label": "PF2E.WeaponPropertyRune.greaterAstral.Name",
            "predicate": [
              "feat:armament-paragon",
              "feat:radiant-armament"
            ],
            "value": "greater-astral"
          },
          {
            "label": "PF2E.WeaponPropertyRune.bane.Name",
            "value": "bane"
          },
          {
            "label": "PF2E.WeaponPropertyRune.brilliant.Name",
            "predicate": [
              "feat:radiant-armament"
            ],
            "value": "brilliant"
          },
          {
            "label": "PF2E.WeaponPropertyRune.greaterBrilliant.Name",
            "predicate": [
              "feat:armament-paragon",
              "feat:radiant-armament"
            ],
            "value": "greater-brilliant"
          },
          {
            "label": "PF2E.WeaponPropertyRune.fearsome.Name",
            "value": "fearsome"
          },
          {
            "label": "PF2E.WeaponPropertyRune.greaterFearsome.Name",
            "predicate": [
              "feat:armament-paragon"
            ],
            "value": "greater-fearsome"
          },
          {
            "label": "PF2E.WeaponPropertyRune.ghostTouch.Name",
            "value": "ghost-touch"
          },
          {
            "label": "PF2E.WeaponPropertyRune.grievous.Name",
            "predicate": [
              "feat:armament-paragon"
            ],
            "value": "grievous"
          },
          {
            "label": "PF2E.WeaponPropertyRune.holy.Name",
            "predicate": [
              "feat:radiant-armament",
              "sanctification:holy"
            ],
            "value": "holy"
          },
          {
            "label": "PF2E.WeaponPropertyRune.keen.Name",
            "predicate": [
              "feat:armament-paragon"
            ],
            "value": "keen"
          },
          {
            "label": "PF2E.WeaponPropertyRune.returning.Name",
            "value": "returning"
          },
          {
            "label": "PF2E.WeaponPropertyRune.shifting.Name",
            "value": "shifting"
          },
          {
            "label": "PF2E.WeaponPropertyRune.unholy.Name",
            "predicate": [
              "feat:radiant-armament",
              "sanctification:unholy"
            ],
            "value": "unholy"
          },
          {
            "label": "PF2E.WeaponPropertyRune.disrupting.Name",
            "value": "disrupting"
          },
          {
            "label": "PF2E.WeaponPropertyRune.greaterDisrupting.Name",
            "predicate": [
              "feat:armament-paragon"
            ],
            "value": "greater-disrupting"
          }
        ],
        "option": "armament-rune",
        "key": "RollOption",
        "selection": "brilliant",
        "toggleable": true,
        "alwaysActive": true,
        "value": true
      },
      {
        "definition": [
          "item:trait:regalia"
        ],
        "key": "AdjustStrike",
        "mode": "add",
        "property": "property-runes",
        "value": "{item|flags.pf2e.rulesSelections.armamentRune}"
      },
      {
        "key": "CriticalSpecialization",
        "predicate": [
          "item:trait:regalia"
        ]
      },
      {
        "key": "RollOption",
        "label": "Bane",
        "option": "bane-type",
        "suboptions": [
          {
            "label": "Aberration",
            "value": "aberration"
          },
          {
            "label": "Animal",
            "value": "animal"
          },
          {
            "label": "Beast",
            "value": "beast"
          },
          {
            "label": "Celestial",
            "value": "celestial"
          },
          {
            "label": "Construct",
            "value": "construct"
          },
          {
            "label": "Dragon",
            "value": "dragon"
          },
          {
            "label": "Elemental",
            "value": "elemental"
          },
          {
            "label": "Fey",
            "value": "fey"
          },
          {
            "label": "Fiend",
            "value": "fiend"
          },
          {
            "label": "Fungus",
            "value": "fungus"
          },
          {
            "label": "Giant",
            "value": "giant"
          },
          {
            "label": "Monitor",
            "value": "monitor"
          },
          {
            "label": "Ooze",
            "value": "ooze"
          },
          {
            "label": "Plant",
            "value": "plant"
          },
          {
            "label": "Undead",
            "value": "undead"
          }
        ],
        "toggleable": true,
        "value": true,
        "predicate": [
          "armament-rune:bane"
        ],
        "alwaysActive": true
      },
      {
        "key": "DamageDice",
        "selector": [
          "strike-damage"
        ],
        "diceNumber": 1,
        "dieSize": "d6",
        "predicate": [
          {
            "and": [
              "item:trait:regalia",
              "target:trait:{item|flags.pf2e.rulesSelections.baneType}",
              "item:rune:property:bane",
              "armament-rune:bane"
            ]
          }
        ],
        "label": "Bane",
        "hideIfDisabled": true
      }
    ],
    "slug": "blessed-armament",
    "_migration": {
      "version": 0.932,
      "lastMigration": null,
      "previous": null
    },
    "traits": {
      "otherTags": [
        "blessing-of-the-devoted"
      ],
      "value": [
        "champion"
      ],
      "rarity": "common"
    },
    "publication": {
      "title": "Pathfinder Player Core 2",
      "authors": "",
      "license": "ORC",
      "remaster": true
    },
    "level": {
      "value": 0
    },
    "category": "classfeature",
    "onlyLevel1": false,
    "maxTakable": 1,
    "actionType": {
      "value": "passive"
    },
    "actions": {
      "value": null
    },
    "prerequisites": {
      "value": []
    },
    "location": null
  },
  "type": "feat",
  "_stats": {
    "compendiumSource": "Compendium.pf2e.classfeatures.Item.EtltLdiy9kNfHU0c",
    "duplicateSource": null,
    "coreVersion": "13.347",
    "systemId": "pf2e",
    "systemVersion": "7.3.1",
    "createdTime": 1728262385702,
    "modifiedTime": 1755999179152,
    "lastModifiedBy": "9BBcVhjS5oHfZWnm",
    "exportSource": null
  },
  "flags": {
    "core": {},
    "scene-packer": {
      "hash": "4a1952ad8342b97dc6b3ba82055f1d101bd6b9f4"
    }
  },
  "effects": [],
  "folder": "rCTbz5Txfuh1dhKi",
  "ownership": {
    "default": 0,
    "ji5YNNUtQqs6Vb3A": 3,
    "5VxTe0CNLISyPuwZ": 3
  },
  "_id": "8S82qBQUx6qJzYTY",
  "sort": 1100000,
  "_key": "!items!8S82qBQUx6qJzYTY"
}
