{
  "name": "Effects",
  "sorting": "a",
  "folder": "QeK4dLeTqtaezB5u",
  "type": "Item",
  "_id": "lX12WXvBxEBf2clb",
  "description": "",
  "sort": 500000,
  "color": null,
  "flags": {
    "scene-packer": {
      "hash": "b43ee319ffe964c2326cd8b6f915528aaef81d44"
    }
  },
  "_stats": {
    "compendiumSource": null,
    "duplicateSource": null,
    "coreVersion": "12.331",
    "systemId": "pf2e",
    "systemVersion": "6.4.0",
    "createdTime": null,
    "modifiedTime": 1728159477265,
    "lastModifiedBy": "Yl6zxDnnyoEj0wIg"
  },
  "_key": "!folders!lX12WXvBxEBf2clb"
}
