{
  "name": "Features",
  "sorting": "a",
  "folder": "wQjsZid7Sxmgr70D",
  "type": "Item",
  "_id": "Lrowc5iak80ZOxGc",
  "description": "",
  "sort": 0,
  "color": null,
  "flags": {
    "scene-packer": {
      "hash": "8045fd40e9e241efbe011624d0c71bca23f16439"
    }
  },
  "_stats": {
    "compendiumSource": null,
    "duplicateSource": null,
    "coreVersion": "12.331",
    "systemId": "pf2e",
    "systemVersion": "6.4.1",
    "createdTime": null,
    "modifiedTime": null,
    "lastModifiedBy": null
  },
  "_key": "!folders!Lrowc5iak80ZOxGc"
}
