{
  "folder": "2FtGmh9Rl1KGzJ9l",
  "name": "Starbound Hero",
  "type": "class",
  "effects": [],
  "system": {
    "description": {
      "gm": "",
      "value": "<p><em>The Cosmos hold within them great power, wisdom and guidance for those who seek it. While some seek the stars for foresight, these knights train their bodies as much as they do their souls. Becoming defenders of the cosmos' plans, or becoming simply being warriors with reverence to the almighty wisdom of the ever-watching stars.</em></p><p><em>Your conduit to divine power eschews the traditional channels of prayer and servitude—you instead glean sacred truths and great mysteries embodied in overarching concepts, whether because you perceive the common ground across multiple deities or circumvent their power entirely.</em></p><p><em>You explore one of these mysteries and draw upon its power to cast miraculous spells, but that power comes with a terrible price: a curse that grows stronger the more you draw upon it, which you might uphold as an instrument of the divine or view as punishment from the gods.</em></p><p><em>@UUID[Compendium.pf2e.journals.JournalEntry.kzxu2dI7tFxv6Ix6.JournalEntryPage.bqaqOx3naiwTozBX]{Oracle}</em></p>"
    },
    "rules": [
      {
        "domain": "all",
        "key": "RollOption",
        "option": "class:oracle",
        "priority": 0
      },
      {
        "domain": "all",
        "key": "RollOption",
        "option": "class:starknight",
        "priority": 0
      },
      {
        "key": "ActiveEffectLike",
        "mode": "override",
        "path": "system.proficiencies.classDCs.oracle.attribute",
        "value": "wis"
      },
      {
        "key": "ActiveEffectLike",
        "mode": "override",
        "path": "system.proficiencies.classDCs.starknight.attribute",
        "value": "wis"
      },
      {
        "key": "ActiveEffectLike",
        "mode": "upgrade",
        "path": "system.proficiencies.classDCs.oracle.rank",
        "value": 1
      },
      {
        "key": "ActiveEffectLike",
        "mode": "upgrade",
        "path": "system.proficiencies.classDCs.starknight.rank",
        "value": 1
      }
    ],
    "slug": "starbound-hero",
    "_migration": {
      "version": 0.942,
      "previous": {
        "schema": 0.935,
        "foundry": "13.348",
        "system": "7.4.3"
      }
    },
    "traits": {
      "otherTags": [],
      "rarity": "unique"
    },
    "publication": {
      "title": "Vyklade's Book of Homebrew",
      "authors": "Vyklade",
      "license": "ORC",
      "remaster": true
    },
    "keyAbility": {
      "value": [
        "cha",
        "wis"
      ],
      "selected": null
    },
    "items": {
      "L3E6d": {
        "uuid": "Compendium.pf2e-misc.our-items.Item.92KTPyRenEPK7HuX",
        "img": "icons/magic/light/swords-light-glowing-white.webp",
        "name": "Astral Armiger",
        "level": 1
      },
      "YePNj": {
        "uuid": "Compendium.pf2e-misc.our-items.Item.VV7VyRtEf7bZAItJ",
        "img": "systems/pf2e/icons/spells/asterism.webp",
        "name": "Cosmic Disciplines",
        "level": 1
      },
      "6yYhW": {
        "uuid": "Compendium.pf2e-misc.our-items.Item.20ew0LMxklG5gKOq",
        "img": "systems/pf2e/icons/spells/levitate.webp",
        "name": "Cosmic Polarities",
        "level": 1
      },
      "OHYKZ": {
        "uuid": "Compendium.pf2e-misc.our-items.Item.rEKeGOp3R4fXwrqU",
        "img": "icons/magic/control/debuff-energy-hold-levitate-blue-yellow.webp",
        "name": "Cosmic Movement",
        "level": 3
      },
      "teXIF": {
        "uuid": "Compendium.pf2e-misc.our-items.Item.tQK0ddwO3LrO2MB2",
        "img": "icons/magic/life/cross-explosion-burst-green.webp",
        "name": "Great Fortitude",
        "level": 3
      },
      "EzvzX": {
        "uuid": "Compendium.pf2e-misc.our-items.Item.RNPtHA10Gh9905F0",
        "img": "icons/creatures/eyes/human-single-blue.webp",
        "name": "Alertness",
        "level": 5
      },
      "C2nay": {
        "uuid": "Compendium.pf2e-misc.our-items.Item.sEIgJwPaBJC6N6MS",
        "img": "icons/magic/light/swords-light-glowing-white.webp",
        "name": "Expanded Armiger",
        "level": 5
      },
      "gVgSw": {
        "uuid": "Compendium.pf2e-misc.our-items.Item.aePyeMPGorq7wbpv",
        "img": "icons/magic/light/swords-light-glowing-white.webp",
        "name": "Boundless Armiger",
        "level": 11
      },
      "NgbmM": {
        "uuid": "Compendium.pf2e-misc.our-items.Item.uhdg4ReEQGFWC78Z",
        "img": "systems/pf2e/icons/features/classes/vigilant-senses.webp",
        "name": "Vigilant Senses",
        "level": 11
      },
      "QKpNT": {
        "uuid": "Compendium.pf2e-misc.our-items.Item.DI65MJeMsWy8s3iU",
        "img": "icons/equipment/chest/breastplate-quilted-brown.webp",
        "name": "Medium Armor Expertise",
        "level": 11
      },
      "D1U5u": {
        "uuid": "Compendium.pf2e-misc.our-items.Item.XiuNvctEPrfcyczu",
        "img": "icons/skills/melee/hand-grip-sword-orange.webp",
        "name": "Greater Weapon Specialization",
        "level": 15
      },
      "xyg7g": {
        "uuid": "Compendium.pf2e-misc.our-items.Item.fyHjQjrsFmcMhM7O",
        "img": "icons/magic/light/explosion-star-glow-blue-purple.webp",
        "name": "Cosmic Mastery",
        "level": 17
      },
      "hvcEO": {
        "uuid": "Compendium.pf2e-misc.our-items.Item.bepRiw3Q0S0SzBBW",
        "img": "icons/magic/light/explosion-star-glow-silhouette.webp",
        "name": "Armiger Mastery",
        "level": 19
      },
      "pWKtR": {
        "uuid": "Compendium.pf2e-misc.our-items.Item.iaxMaBuaA8gB4cic",
        "img": "systems/pf2e/icons/features/classes/improved-evasion.webp",
        "name": "Improved Evasion",
        "level": 17
      },
      "Hw5EL": {
        "uuid": "Compendium.pf2e-misc.our-items.Item.c9CaJ8rjGzoS13Pj",
        "img": "icons/magic/light/orbs-smoke-pink.webp",
        "name": "Cosmic Expertise",
        "level": 7
      },
      "5FiQo": {
        "uuid": "Compendium.pf2e-misc.our-items.Item.UtsxWKhGUFjex5Hp",
        "img": "icons/magic/fire/explosion-embers-evade-silhouette.webp",
        "name": "Evasion",
        "level": 7
      },
      "XJVfe": {
        "uuid": "Compendium.pf2e-misc.our-items.Item.ChBmER95zO1s1F4m",
        "img": "systems/pf2e/icons/features/classes/weapon-specialization.webp",
        "name": "Weapon Specialization",
        "level": 7
      },
      "oEvuB": {
        "uuid": "Compendium.pf2e-misc.our-items.Item.5BTWgJ1hwFuzT0jg",
        "img": "icons/equipment/chest/breastplate-collared-steel.webp",
        "name": "Medium Armor Mastery",
        "level": 19
      },
      "eKfDH": {
        "uuid": "Compendium.pf2e-misc.our-items.Item.1WE1ezTingOSvBcT",
        "img": "icons/magic/light/hand-sparks-glow-yellow.webp",
        "name": "Practiced Discipline",
        "level": 5
      },
      "3l7VS": {
        "uuid": "Compendium.pf2e-misc.our-items.Item.BdY9NLaeDAXIxDTX",
        "img": "icons/skills/melee/hand-grip-sword-red.webp",
        "name": "Weapon Expertise",
        "level": 5
      },
      "j2Eek": {
        "uuid": "Compendium.pf2e-misc.our-items.Item.uQxZ3nxkSyNFtoxO",
        "img": "icons/magic/light/hand-sparks-glow-yellow.webp",
        "name": "Practiced Discipline",
        "level": 9
      },
      "yiwn8": {
        "uuid": "Compendium.pf2e-misc.our-items.Item.df43qSLDwrfQ5XQ4",
        "img": "icons/magic/light/hand-sparks-glow-yellow.webp",
        "name": "Practiced Discipline",
        "level": 13
      },
      "OSByD": {
        "uuid": "Compendium.pf2e-misc.our-items.Item.Ed5p0pk61G1ANoPz",
        "img": "icons/creatures/mammals/bull-horns-eyes-glowin-orange.webp",
        "name": "Resolve",
        "level": 13
      },
      "tMOnP": {
        "uuid": "Compendium.pf2e-misc.our-items.Item.yx8CRigvm0BWBury",
        "img": "icons/magic/light/hand-sparks-glow-yellow.webp",
        "name": "Practiced Discipline",
        "level": 17
      },
      "nTH62": {
        "uuid": "Compendium.pf2e-misc.our-items.Item.CbNX5M0AZxEXpbnx",
        "img": "icons/skills/melee/blade-tip-chipped-blood-red.webp",
        "name": "Weapon Mastery",
        "level": 13
      },
      "sJJUf": {
        "uuid": "Compendium.pf2e.classfeatures.Item.7AVspOB6ITNzGFZi",
        "img": "icons/weapons/axes/axe-double-gold.webp",
        "name": "Oracle Spellcasting",
        "level": 1
      },
      "U713k": {
        "uuid": "Compendium.pf2e.classfeatures.Item.PRJYLksQEwT39bTl",
        "img": "icons/magic/symbols/question-stone-yellow.webp",
        "name": "Mystery",
        "level": 1
      },
      "qZHwL": {
        "uuid": "Compendium.pf2e.classfeatures.Item.ibX2EhKkyUtbOHLj",
        "img": "icons/sundries/scrolls/scroll-runed-brown.webp",
        "name": "Oracular Curse",
        "level": 1
      },
      "GhHRh": {
        "uuid": "Compendium.pf2e.classfeatures.Item.NXUOtO9NytHQurlg",
        "img": "systems/pf2e/icons/features/classes/revelation-spells.webp",
        "name": "Revelation Spells",
        "level": 1
      },
      "9BEik": {
        "uuid": "Compendium.pf2e.classfeatures.Item.1RfnAiyQ5FR7vnuH",
        "img": "icons/sundries/books/book-symbol-spiral-silver-blue.webp",
        "name": "Spell Repertoire",
        "level": 1
      },
      "09sB4": {
        "uuid": "Compendium.pf2e.classfeatures.Item.VKRjmXxBFLrJK01c",
        "img": "systems/pf2e/icons/features/classes/signature-spells-sorcerer.webp",
        "name": "Signature Spells",
        "level": 3
      },
      "OMTli": {
        "uuid": "Compendium.pf2e.classfeatures.Item.cCTqkTHYnVCJKg4S",
        "img": "icons/creatures/mammals/bull-horns-eyes-glowin-orange.webp",
        "name": "Mysterious Resolve",
        "level": 3
      },
      "rJRHe": {
        "uuid": "Compendium.pf2e.classfeatures.Item.cD3nSupdCvONuHiE",
        "img": "icons/sundries/books/book-backed-silver-gold.webp",
        "name": "Expert Spellcaster",
        "level": 7
      },
      "meoE5": {
        "uuid": "Compendium.pf2e.classfeatures.Item.70jqXP2eS4tRZ0Ok",
        "img": "systems/pf2e/icons/features/classes/magical-fortitude.webp",
        "name": "Magical Fortitude",
        "level": 9
      },
      "eMwiV": {
        "uuid": "Compendium.pf2e.classfeatures.Item.rrzItB68Er0DzKx7",
        "img": "systems/pf2e/icons/features/classes/major-curse.webp",
        "name": "Major Curse",
        "level": 11
      },
      "ZQWmY": {
        "uuid": "Compendium.pf2e.classfeatures.Item.iwAzV1IlQ2pMHQoB",
        "img": "icons/sundries/scrolls/scroll-yellow-teal.webp",
        "name": "Divine Access",
        "level": 11
      },
      "OQazB": {
        "uuid": "Compendium.pf2e.classfeatures.Item.eTQZQGPMIZJHIR6J",
        "img": "icons/creatures/eyes/human-single-blue.webp",
        "name": "Oracular Senses",
        "level": 11
      },
      "ztYZu": {
        "uuid": "Compendium.pf2e.classfeatures.Item.tIpJHInpblTed5ZK",
        "img": "icons/magic/symbols/symbol-lightning-bolt.webp",
        "name": "Premonition Reflexes",
        "level": 13
      },
      "POsxs": {
        "uuid": "Compendium.pf2e.classfeatures.Item.l1InYvhnQSz6Ucxc",
        "img": "icons/skills/trades/academics-book-study-purple.webp",
        "name": "Master Spellcaster",
        "level": 15
      },
      "NhT0U": {
        "uuid": "Compendium.pf2e.classfeatures.Item.Kj59CmXnMJDKXKWx",
        "img": "systems/pf2e/icons/features/classes/greater-resolve.webp",
        "name": "Greater Mysterious Resolve",
        "level": 17
      },
      "qfGK7": {
        "uuid": "Compendium.pf2e.classfeatures.Item.F4brPlp1tHGUqyuI",
        "img": "icons/equipment/neck/necklace-carved-bone-skull.webp",
        "name": "Extreme Curse",
        "level": 17
      },
      "2o6kt": {
        "uuid": "Compendium.pf2e.classfeatures.Item.Hfaa7TuLn3nE8lr3",
        "img": "icons/sundries/books/book-open-purple.webp",
        "name": "Legendary Spellcaster",
        "level": 19
      },
      "MGJji": {
        "uuid": "Compendium.pf2e.classfeatures.Item.571c1aGnvNVwfF6b",
        "img": "icons/sundries/lights/candle-lit-angelic.webp",
        "name": "Oracular Clarity",
        "level": 19
      },
      "9Fuwf": {
        "uuid": "Compendium.pf2e-misc.our-items.Item.HWNvRM0c5cZrwM8v",
        "img": "systems/pf2e/icons/spells/enduring-might.webp",
        "name": "Dual Class Attribute",
        "level": 1
      }
    },
    "hp": 10,
    "trainedSkills": {
      "value": [
        "occultism",
        "religion"
      ],
      "additional": 3
    },
    "perception": 1,
    "savingThrows": {
      "fortitude": 1,
      "reflex": 2,
      "will": 2
    },
    "attacks": {
      "simple": 1,
      "martial": 1,
      "advanced": 0,
      "unarmed": 1,
      "other": {
        "name": "",
        "rank": 0
      }
    },
    "defenses": {
      "unarmored": 1,
      "light": 1,
      "medium": 1,
      "heavy": 0
    },
    "spellcasting": 1,
    "ancestryFeatLevels": {
      "value": [
        1,
        5,
        9,
        13,
        17
      ]
    },
    "classFeatLevels": {
      "value": [
        1,
        2,
        4,
        6,
        8,
        10,
        12,
        14,
        16,
        18,
        20
      ]
    },
    "generalFeatLevels": {
      "value": [
        3,
        7,
        11,
        15,
        19
      ]
    },
    "skillFeatLevels": {
      "value": [
        1,
        2,
        3,
        4,
        6,
        7,
        8,
        10,
        12,
        14,
        15,
        16,
        18,
        20
      ]
    },
    "skillIncreaseLevels": {
      "value": [
        3,
        5,
        7,
        9,
        11,
        13,
        15,
        17,
        19
      ]
    }
  },
  "img": "modules/pf2e-misc/assets/icons/Starknight.webp",
  "flags": {
    "scene-packer": {
      "hash": "f0cec4e2e9d2c05888bc939db7eeb3cb91aa7aa3",
      "sourceId": "Item.joViDziuVtRAnhl7"
    }
  },
  "_stats": {
    "compendiumSource": null,
    "duplicateSource": null,
    "exportSource": null,
    "coreVersion": "13.348",
    "systemId": "pf2e",
    "systemVersion": "7.4.3",
    "createdTime": 1756541543803,
    "modifiedTime": 1758047472620,
    "lastModifiedBy": "Yl6zxDnnyoEj0wIg"
  },
  "ownership": {
    "default": 0,
    "9BBcVhjS5oHfZWnm": 3
  },
  "_id": "Z2p6XEJFHkPf2tlj",
  "sort": 100000,
  "_key": "!items!Z2p6XEJFHkPf2tlj"
}
